sharp/__init__.py
sharp/_measures.py
sharp/_min_dependencies.py
sharp/_version.py
sharp/base.py
sharp/metrics/__init__.py
sharp/metrics/_base.py
sharp/metrics/_consistency.py
sharp/metrics/_fidelity.py
sharp/metrics/_sensitivity.py
sharp/metrics/tests/__init__.py
sharp/metrics/tests/test_base.py
sharp/metrics/tests/test_fidelity.py
sharp/qoi/__init__.py
sharp/qoi/_qoi.py
sharp/qoi/base.py
sharp/qoi/tests/__init__.py
sharp/qoi/tests/test_qoi.py
sharp/qoi/tests/test_top_k.py
sharp/tests/__init__.py
sharp/tests/test_base.py
sharp/tests/test_basic_usage.py
sharp/tests/test_docstrings.py
sharp/utils/__init__.py
sharp/utils/_checks.py
sharp/utils/_parallelize.py
sharp/utils/_rank_utils.py
sharp/utils/_show_versions.py
sharp/utils/_testing.py
sharp/utils/_utils.py
sharp/visualization/__init__.py
sharp/visualization/_aggregate.py
sharp/visualization/_visualization.py
sharp/visualization/_waterfall.py
xai_sharp-0.1.1.dist-info/licenses/LICENSE
xai_sharp-0.1.1.dist-info/METADATA
xai_sharp-0.1.1.dist-info/WHEEL
xai_sharp-0.1.1.dist-info/top_level.txt
xai_sharp-0.1.1.dist-info/RECORD
