Metadata-Version: 2.4
Name: xai-sharp
Version: 0.1.1
Summary: Implementation of the ShaRP framework.
Home-page: https://github.com/DataResponsibly/sharp
Download-URL: https://github.com/DataResponsibly/sharp
Maintainer: J. Fonseca
Maintainer-email: jpfonseca@novaims.unl.pt
License: MIT
Classifier: Intended Audience :: Science/Research
Classifier: Intended Audience :: Developers
Classifier: License :: OSI Approved
Classifier: Programming Language :: Python
Classifier: Topic :: Software Development
Classifier: Topic :: Scientific/Engineering
Classifier: Operating System :: Microsoft :: Windows
Classifier: Operating System :: POSIX
Classifier: Operating System :: Unix
Classifier: Operating System :: MacOS
Classifier: Programming Language :: Python :: 3.9
Classifier: Programming Language :: Python :: 3.10
Classifier: Programming Language :: Python :: 3.11
Classifier: Programming Language :: Python :: 3.12
License-File: LICENSE
Requires-Dist: numpy>=1.20.0
Requires-Dist: pandas>=1.3.5
Requires-Dist: scikit-learn>=1.2.0
Requires-Dist: tqdm>=4.46.0
Provides-Extra: optional
Requires-Dist: matplotlib>=2.2.3; extra == "optional"
Provides-Extra: docs
Requires-Dist: matplotlib>=2.2.3; extra == "docs"
Requires-Dist: sphinx>=4.2.0; extra == "docs"
Requires-Dist: numpydoc>=1.0.0; extra == "docs"
Requires-Dist: sphinxawesome-theme>=5.0.0; extra == "docs"
Requires-Dist: recommonmark>=0.7.1; extra == "docs"
Requires-Dist: sphinx-markdown-tables>=0.0.17; extra == "docs"
Requires-Dist: sphinx-gallery>=0.15.0; extra == "docs"
Provides-Extra: examples
Provides-Extra: tests
Requires-Dist: pytest-cov>=3.0.0; extra == "tests"
Requires-Dist: flake8>=3.8.2; extra == "tests"
Requires-Dist: black>=22.3; extra == "tests"
Requires-Dist: pylint>=2.12.2; extra == "tests"
Requires-Dist: mypy>=1.6.1; extra == "tests"
Requires-Dist: types-requests>=2.31.0.10; extra == "tests"
Requires-Dist: coverage>=6.2; extra == "tests"
Requires-Dist: numpydoc>=1.0.0; extra == "tests"
Provides-Extra: all
Requires-Dist: numpy>=1.20.0; extra == "all"
Requires-Dist: pandas>=1.3.5; extra == "all"
Requires-Dist: scikit-learn>=1.2.0; extra == "all"
Requires-Dist: tqdm>=4.46.0; extra == "all"
Requires-Dist: matplotlib>=2.2.3; extra == "all"
Requires-Dist: pytest-cov>=3.0.0; extra == "all"
Requires-Dist: flake8>=3.8.2; extra == "all"
Requires-Dist: black>=22.3; extra == "all"
Requires-Dist: pylint>=2.12.2; extra == "all"
Requires-Dist: mypy>=1.6.1; extra == "all"
Requires-Dist: types-requests>=2.31.0.10; extra == "all"
Requires-Dist: coverage>=6.2; extra == "all"
Requires-Dist: sphinx>=4.2.0; extra == "all"
Requires-Dist: numpydoc>=1.0.0; extra == "all"
Requires-Dist: sphinxawesome-theme>=5.0.0; extra == "all"
Requires-Dist: recommonmark>=0.7.1; extra == "all"
Requires-Dist: sphinx-markdown-tables>=0.0.17; extra == "all"
Requires-Dist: sphinx-gallery>=0.15.0; extra == "all"
Dynamic: classifier
Dynamic: description
Dynamic: description-content-type
Dynamic: download-url
Dynamic: home-page
Dynamic: license
Dynamic: license-file
Dynamic: maintainer
Dynamic: maintainer-email
Dynamic: provides-extra
Dynamic: requires-dist
Dynamic: summary
